topsis.py
Topsis_Laksh_101916002-0.0.6.dist-info/METADATA
Topsis_Laksh_101916002-0.0.6.dist-info/WHEEL
Topsis_Laksh_101916002-0.0.6.dist-info/top_level.txt
Topsis_Laksh_101916002-0.0.6.dist-info/RECORD
